fltk/__init__.py
fltk/fltk.py
fltk/doc/Makefile
fltk/doc/conf.py
fltk/doc/dessins.rst
fltk/doc/effacer.rst
fltk/doc/evenements.rst
fltk/doc/index.rst
fltk/doc/intro.rst
fltk/doc/_static/style.css
fltk/doc/_templates/agogo2/layout.html
fltk/doc/_templates/agogo2/page.html.old
fltk/doc/_templates/agogo2/theme.conf
fltk/doc/_templates/agogo2/static/agogo.css_t
fltk/doc/_templates/agogo2/static/bgfooter.png
fltk/doc/_templates/agogo2/static/bgtop.png
fltk/doc/ex/Pipfile
fltk/doc/ex/cercle.py
fltk/doc/ex/cerclesCouleur.py
fltk/doc/ex/ding.mp3
fltk/doc/ex/ding.wav
fltk/doc/ex/efface.py
fltk/doc/ex/emoji.png
fltk/doc/ex/ev_quit.py
fltk/doc/ex/ev_redim.py
fltk/doc/ex/fleches.py
fltk/doc/ex/fltk.py
fltk/doc/ex/image.py
fltk/doc/ex/ligne.py
fltk/doc/ex/ligneCouleur.py
fltk/doc/ex/log-ev-clavier.py
fltk/doc/ex/log-ev-faux.py
fltk/doc/ex/log-ev-ou-none.py
fltk/doc/ex/log-ev-quitte.py
fltk/doc/ex/log-ev-reels.py
fltk/doc/ex/log-ev-souris.py
fltk/doc/ex/modifie.py
fltk/doc/ex/mypy.xml
fltk/doc/ex/petit-carre-ameliore.py
fltk/doc/ex/petit-carre.py
fltk/doc/ex/picturize.py
fltk/doc/ex/pylint.json
fltk/doc/ex/rectangles.py
fltk/doc/ex/rectanglesCouleur.py
fltk/doc/ex/rectanglesPlein.py
fltk/doc/ex/repere.py
fltk/doc/ex/rotation_zoom.py
fltk/doc/ex/smiley.gif
fltk/doc/ex/smiley.png
fltk/doc/ex/smiley2.gif
fltk/doc/ex/smiley2.png
fltk/doc/ex/son.py
fltk/doc/ex/survol.py
fltk/doc/ex/template-ev.py
fltk/doc/ex/template.py
fltk/doc/ex/texte.py
fltk/doc/ex/texteCentre.py
fltk/doc/ex/texteEncadre.py
fltk/doc/images/cercle.png
fltk/doc/images/cerclesCouleur.png
fltk/doc/images/efface-2.png
fltk/doc/images/efface-3.png
fltk/doc/images/efface-anim.png
fltk/doc/images/efface.png
fltk/doc/images/fleches.png
fltk/doc/images/image.png
fltk/doc/images/image.tiff
fltk/doc/images/ligne.png
fltk/doc/images/ligneCouleur.png
fltk/doc/images/ligneCouleur2.png
fltk/doc/images/pixels.png
fltk/doc/images/rectangles.png
fltk/doc/images/rectanglesCouleur.png
fltk/doc/images/rectanglesPlein.png
eiffeltk-2025.1.dist-info/METADATA
eiffeltk-2025.1.dist-info/WHEEL
eiffeltk-2025.1.dist-info/licenses/LICENSE.txt
eiffeltk-2025.1.dist-info/RECORD
